{
  "Employee": [
    {
      "id": 1,
      "BookName": "Bible Stories",
      "Author": "John",
      "Content": "Hearts is a trick taking card game in which players try to avoid taking penalty cards.It is game is closely related to other cards games like whist or bridge",
      "Date": "19-02-2012",
      "Likes": 2,
      "change": false,
      "show": false,
      "imageUrl": "assets/images/OIP.jpg",
      "authorUrl": "assets/images/Author3.jpg"
    },
    {
      "id": 2,
      "BookName": "Mystery Book",
      "Author": "Simon",
      "Content": "Hearts is a trick taking card game in which players try to avoid taking penalty cards.It is game is closely related to other cards games like whist or bridge",
      "Date": "19-02-2012",
      "Likes": 3,
      "change": false,
      "show": false,
      "imageUrl": "assets/images/Author6.jpg",
      "authorUrl": "assets/images/Author4.jpg"
    },
    {
      "id": 3,
      "BookName": "A Game Of Hearts",
      "Author": "M.A Lee",
      "Content": "Hearts is a trick taking card game in which players try to avoid taking penalty cards.It is game is closely related to other cards games like whist or bridge",
      "Date": "19-02-2012",
      "Likes": "3",
      "change": false,
      "show": false,
      "imageUrl": "assets/images/Author5.jpg",
      "authorUrl": "assets/images/Author1.jpg"
    },
    {
      "id": 4,
      "BookName": "Mayura",
      "Author": "Trainer",
      "Content": "Hearts is a trick taking card game in which players try to avoid taking penalty cards.It is game is closely related to other cards games like whist or bridge",
      "Date": "19-02-2012",
      "Likes": "3",
      "change": false,
      "show": false,
      "imageUrl": "assets/images/OIP.jpg",
      "authorUrl": "assets/images/Author1.jpg"
    },
    {
      "id": 5,
      "BookName": "Rahul",
      "Author": "Trainer",
      "Content": "Hearts is a trick taking card game in which players try to avoid taking penalty cards.It is game is closely related to other cards games like whist or bridge",
      "Date": "19-02-2012",
      "Likes": 4,
      "change": false,
      "show": false,
      "imageUrl": "assets/images/OIP.jpg",
      "authorUrl": "assets/images/Author1.jpg"
    },
    {
      "id": 2,
      "BookName": "Mystery Book",
      "Author": "Simon",
      "Content": "Hearts is a trick taking card game in which players try to avoid taking penalty cards.It is game is closely related to other cards games like whist or bridge",
      "Date": "19-02-2012",
      "Likes": 3,
      "change": false,
      "show": false,
      "imageUrl": "assets/images/Author6.jpg",
      "authorUrl": "assets/images/Author4.jpg"
    },
    {
      "id": "18",
      "BookName": "Focus",
      "Author": "Mik",
      "Date": "2022-04-14"
    }
  ],
  "User": [
    {
      "totalBook": 3,
      "id": 2,
      "email": "user1@gmail.com"
    }
  ]
}